LICENSE
setup.py
isu_engr_1600_python/__init__.py
isu_engr_1600_python/activity_1.py
isu_engr_1600_python.egg-info/PKG-INFO
isu_engr_1600_python.egg-info/SOURCES.txt
isu_engr_1600_python.egg-info/dependency_links.txt
isu_engr_1600_python.egg-info/top_level.txt