Metadata-Version: 2.1
Name: isu-engr-1600-python
Version: 0.0.3
Summary: A example Python package
Home-page: https://github.com/shuds13/pyexample
Author: Stephen Hudson
Author-email: daking@iastate.edu
License: BSD 2-clause
Classifier: Development Status :: 1 - Planning
Classifier: Intended Audience :: Science/Research
Classifier: License :: OSI Approved :: BSD License
Classifier: Operating System :: POSIX :: Linux
Classifier: Programming Language :: Python :: 3.10
License-File: LICENSE
